pandashare/__init__.py
pandashare/pro/__init__.py
pandashare/pro/client.py
pandashare/pro/data_pro.py
pandashare/stock/__init__.py
pandashare/stock/cons.py
pandashare/util/__init__.py
pandashare/util/upass.py
pandashare-0.0.6.dist-info/LICENSE
pandashare-0.0.6.dist-info/METADATA
pandashare-0.0.6.dist-info/WHEEL
pandashare-0.0.6.dist-info/top_level.txt
pandashare-0.0.6.dist-info/RECORD
