Metadata-Version: 2.1
Name: pandashare
Version: 0.0.6
Summary: Sharing data focused on financial AI
Home-page: https://github.com/quantdrchow/pandashare
Author: quantdrchow
Author-email: quantdrchow@gmail.com
License: MIT
Classifier: Programming Language :: Python :: 3
Classifier: License :: OSI Approved :: MIT License
Classifier: Operating System :: OS Independent
License-File: LICENSE
